sys_tools/__init__.py
sys_tools/plugin.py
sys_tools/security.py
sys_tools/utils.py
agentup_sys_tools-0.1.0.dist-info/METADATA
agentup_sys_tools-0.1.0.dist-info/WHEEL
agentup_sys_tools-0.1.0.dist-info/entry_points.txt
agentup_sys_tools-0.1.0.dist-info/licenses/LICENSE
agentup_sys_tools-0.1.0.dist-info/RECORD
